[
    {"name": "3M", "src": "3m.jpg"},
    {"name": "ABB", "src": "abb.jpg"},
    {"name": "Abbott", "src": "abbott.jpg"},
    {"name": "Abbvie", "src": "abbvie.jpg"},
    {"name": "ACNielsen", "src": "acnielsen.jpg"},
    {"name": "AIR LIQUIDE", "src": "air_liquide.jpg"},
    {"name": "Akzo Nobel", "src": "akzo_nobel.png"},
    {"name": "ALBA", "src": "alba.jpg"},
    {"name": "Alicorp", "src": "alicorp.jpg"},
    {"name": "aluar Aluminio Argentino", "src": "aluar_aluminio_argentino.jpg"},
    {"name": "América", "src": "america.jpg"},
    {"name": "Andreani", "src": "andreani.jpg"},
    {"name": "Arsat", "src": "arsat.jpg"},
    {"name": "Asignet Communications DNA", "src": "asignet_communications_dna.jpg"},
    {"name": "Asociación de Anestesia", "src": "asociacion_de_anestesia.jpg"},
    {"name": "Asofarma", "src": "asofarma.jpg"},
    {"name": "Assetco", "src": "assetco.jpg"},
    {"name": "Assist Card", "src": "assist_card.jpg"},
    {"name": "AudioCodes", "src": "audiocodes.jpg"},
    {"name": "Autopistas Del Sol", "src": "autopistas_del_sol.jpg"},
    {"name": "Autotrol", "src": "autotrol.jpg"},
    {"name": "Axion Energy", "src": "axion_energy.jpg"},
    {"name": "Baker Hugues", "src": "baker_hughes.png"},
    {"name": "BGH", "src": "bgh.jpg"},
    {"name": "BI Estudio", "src": "bi_estudio.jpg"},
    {"name": "BNP Paribas", "src": "bnp_paribas.jpg"},
    {"name": "Bocatti", "src": "bocatti.jpg"},
    {"name": "Bogs", "src": "bogs.png"},
    {"name": "Bridgestone", "src": "bridgestone.jpg"},
    {"name": "Bristol Myers Squibb", "src": "bristol_myers_squibb.jpg"},
    {"name": "BTS Credilogros", "src": "bts_credilogros.jpg"},
    {"name": "BVS", "src": "bvs.png"},
    {"name": "Camarco", "src": "camarco.jpg"},
    {"name": "Capilatis", "src": "capilatis.jpg"},
    {"name": "Cargill", "src": "cargill.jpg"},
    {"name": "Carrier", "src": "carrier.jpg"},
    {"name": "Casa Salesiana Don Bosco", "src": "casa_salesiana_don_bosco.jpg"},
    {"name": "Casasco", "src": "casasco.jpg"},
    {"name": "Cerámica San Lorenzo", "src": "ceramica_san_lorenzo.jpg"},
    {"name": "Cerveceria y Malteria Quilmes", "src": "cerveceria_y_malteria_quilmes.jpg"},
    {"name": "Chrysler", "src": "chrysler.jpg"},
    {"name": "Ciencia & Tecnología en Imágenes", "src": "ciencia_&_tecnologia_en_imagenes.jpg"},
    {"name": "Cisco", "src": "cisco.jpg"},
    {"name": "Clama", "src": "clama.jpg"},
    {"name": "Clarian Health", "src": "clarian_health.jpg"},
    {"name": "Clariant", "src": "clariant.jpg"},
    {"name": "Claro", "src": "claro.jpg"},
    {"name": "CMD", "src": "cmd.jpg"},
    {"name": "Coasin", "src": "coasin.jpg"},
    {"name": "Coca Cola", "src": "coca_cola.jpg"},
    {"name": "Coca Cola Femsa", "src": "coca_cola_femsa.jpg"},
    {"name": "Colegio Público de Abogados", "src": "colegio_publico_de_abogados.jpg"},
    {"name": "Compania Hasar", "src": "compania_hasar.jpg"},
    {"name": "Consejo Profesional de Ciencias Económicas de la Ciudad de Bs As", "src": "consejo_profesional_de_ciencias_economicas_de_la_ciudad_de_bs_as.jpg"},
    {"name": "Consultores Soluciones Informáticas", "src": "consultores_soluciones_informaticas.jpg"},
    {"name": "Cooperativa Electrica Lujan", "src": "cooperativa_electrica_lujan.jpg"},
    {"name": "Corte Suprema de Justicia", "src": "corte_suprema_de_justicia.png"},
    {"name": "Cotelcam Comunicaciones", "src": "cotelcam_comunicaciones.jpg"},
    {"name": "Coto", "src": "coto.jpg"},
    {"name": "Covedisa", "src": "covedisa.jpg"},
    {"name": "CPS Comunicaciones", "src": "cps_comunicaciones.jpg"},
    {"name": "CRIBA", "src": "criba.jpg"},
    {"name": "Cruz del Sur", "src": "cruz_del_sur.jpg"},
    {"name": "Delta Asset Management", "src": "delta_asset_management.png"},
    {"name": "Dia %", "src": "dia.jpg"},
    {"name": "Diksha", "src": "diksha.jpg"},
    {"name": "Dilexis", "src": "dilexis.jpg"},
    {"name": "Disco", "src": "disco.jpg"},
    {"name": "Disney", "src": "disney.jpg"},
    {"name": "Disprofarma", "src": "disprofarma.jpg"},
    {"name": "Dte", "src": "dte.png"},
    {"name": "Duke Energy", "src": "duke_energy.jpg"},
    {"name": "Dupont", "src": "dupont.jpg"},
    {"name": "Eaton", "src": "eaton.jpg"},
    {"name": "Edelap", "src": "edelap.jpg"},
    {"name": "Eg3", "src": "eg3.jpg"},
    {"name": "Elastec", "src": "elastec.jpg"},
    {"name": "Elster", "src": "elster.jpg"},
    {"name": "Enacom", "src": "enacom.jpg"},
    {"name": "Enerminds", "src": "enerminds.jpg"},
    {"name": "Ericsson", "src": "ericsson.jpg"},
    {"name": "Esso", "src": "esso.jpg"},
    {"name": "Eurofarma", "src": "eurofarma.jpg"},
    {"name": "Europ Assistance", "src": "europ_assistance.png"},
    {"name": "Exo logística", "src": "exo_logistica.jpg"},
    {"name": "Exolgan", "src": "exolgan.jpg"},
    {"name": "Faaaar", "src": "faaaar.jpg"},
    {"name": "Farmalink", "src": "farmalink.jpg"},
    {"name": "Flex N Gate", "src": "flex_n_gate.jpg"},
    {"name": "Formar", "src": "formar.jpg"},
    {"name": "Fortalein", "src": "fortalein.png"},
    {"name": "Forvia", "src": "forvia.png"},
    {"name": "Fravega", "src": "fravega.jpg"},
    {"name": "Gefco", "src": "gefco.jpg"},
    {"name": "Genoma Lab Internacional", "src": "genomma_lab_internacional.jpg"},
    {"name": "Genzyme", "src": "genzyme.jpg"},
    {"name": "Grace", "src": "grace.jpg"},
    {"name": "Grace Holdings", "src": "grace_holdings.jpg"},
    {"name": "Gruipo datco", "src": "gruipo_datco.jpg"},
    {"name": "Grupo Assa", "src": "grupo_assa.jpg"},
    {"name": "Grupo Hasar", "src": "grupo_hasar.jpg"},
    {"name": "Grupo Imas", "src": "grupo_imas.jpg"},
    {"name": "Hasar Sistemas", "src": "hasar_sistemas.jpg"},
    {"name": "Holcim", "src": "holcim.jpg"},
    {"name": "Honeywell", "src": "honeywell.png"},
    {"name": "Ican", "src": "ican.jpg"},
    {"name": "Ike asistencia argentina", "src": "ike_asistencia_argentina.jpg"},
    {"name": "Ingram Micro", "src": "ingram_micro.jpg"},
    {"name": "Intekno Argentina", "src": "intekno_argentina.jpg"},
    {"name": "Interbanking", "src": "interbanking.jpg"},
    {"name": "Interconnect", "src": "interconnect.jpg"},
    {"name": "International Star", "src": "international_star.jpg"},
    {"name": "Iplan", "src": "iplan.jpg"},
    {"name": "Itg Argentina", "src": "itg_argentina.jpg"},
    {"name": "Jica", "src": "jica.jpg"},
    {"name": "Jumbo Cencosud", "src": "jumbo_cencosud.jpg"},
    {"name": "Kimberly Clark", "src": "kimberly_clark.jpg"},
    {"name": "Laboratorio Elea", "src": "laboratorio_elea.jpg"},
    {"name": "Larousse", "src": "larousse.jpg"},
    {"name": "Ledesma", "src": "ledesma.jpg"},
    {"name": "Liag Argentina", "src": "liag_argentina.jpg"},
    {"name": "Llao Llao Hotel & Resort", "src": "llao_llao_hotel_&_resort.jpg"},
    {"name": "Logicalis", "src": "logicalis.jpg"},
    {"name": "Loreal", "src": "loreal.jpg"},
    {"name": "Los Cinco Hispanos", "src": "los_cinco_hispanos.png"},
    {"name": "Luis Pasteaur", "src": "luis_pasteaur.jpg"},
    {"name": "Macro", "src": "macro.jpg"},
    {"name": "Macronet", "src": "macronet.jpg"},
    {"name": "Makro", "src": "makro.jpg"},
    {"name": "Mapa Virulana", "src": "mapa_virulana.jpg"},
    {"name": "Marby", "src": "marby.jpg"},
    {"name": "Marfrig", "src": "marfrig.jpg"},
    {"name": "Masisa", "src": "masisa.jpg"},
    {"name": "Matertel", "src": "matertel.jpg"},
    {"name": "Medel", "src": "medel.jpg"},
    {"name": "Media Monks", "src": "media_monks.jpg"},
    {"name": "Media8 Digital Marketing", "src": "media8_digital_marketing.jpg"},
    {"name": "Merial", "src": "merial.jpg"},
    {"name": "Metalpar", "src": "metalpar.jpg"},
    {"name": "Microglobal", "src": "microglobal.jpg"},
    {"name": "Ministerio de Trabajo y Asuntos Sociales", "src": "ministerio_de_trabajo_y_asuntos_sociales.jpg"},
    {"name": "Mirgor", "src": "mirgor.jpg"},
    {"name": "Monsanto", "src": "monsanto.jpg"},
    {"name": "Movistar", "src": "movistar.jpg"},
    {"name": "Msd Merck Sharp & Dohme", "src": "msd_merck_sharp_&_dohme.jpg"},
    {"name": "Natura", "src": "natura.jpg"},
    {"name": "Nec", "src": "nec.jpg"},
    {"name": "Netizen Telecomunicaciones", "src": "netizen_telecomunicaciones.jpg"},
    {"name": "Newell Rubbermaid", "src": "newell_rubbermaid.jpg"},
    {"name": "NH City Hotel", "src": "nh_city_hotel.png"},
    {"name": "Nielsen", "src": "nielsen.jpg"},
    {"name": "Nike", "src": "nike.jpg"},
    {"name": "Nissan", "src": "nissan.jpg"},
    {"name": "Nobleza Piccardo", "src": "nobleza_piccardo.jpg"},
    {"name": "Non Stop", "src": "non_stop.jpg"},
    {"name": "Novartis", "src": "novartis.jpg"},
    {"name": "Nueva Cristaleria Rosario", "src": "nueva_cristaleria_rosario.jpg"},
    {"name": "OLX", "src": "olx.png"},
    {"name": "Oblak", "src": "oblak.jpg"},
    {"name": "Orange Business Services", "src": "orange_business_services.jpg"},
    {"name": "Ottobock Argentina", "src": "ottobock_argentina.png"},
    {"name": "Paladini", "src": "paladini.jpg"},
    {"name": "Pampa Energia", "src": "pampa_energia.jpg"},
    {"name": "Pan American Energy", "src": "pan_american_energy.png"},
    {"name": "PDA", "src": "pda.png"},
    {"name": "Penguin Random House", "src": "penguin_random_house.png"},
    {"name": "Pepsico Argentina", "src": "pepsico_argentina.jpg"},
    {"name": "Pirelli", "src": "pirelli.png"},
    {"name": "Ppg Industries Arg", "src": "ppg_industries_arg.jpg"},
    {"name": "Quickfood", "src": "quickfood.png"},
    {"name": "Real Embajada de Noruega", "src": "real_embajada_de_noruega.jpg"},
    {"name": "Reckitt Benckiser", "src": "reckitt_benckiser.jpg"},
    {"name": "Rta Radio y Television Argentina", "src": "rta_radio_y_television_argentina.jpg"},
    {"name": "Sadesa", "src": "sadesa.jpg"},
    {"name": "Samsung Argentina", "src": "samsung_argentina.jpg"},
    {"name": "Sanford Brands", "src": "sanford_brands.jpg"},
    {"name": "Sanofi Genzyme", "src": "sanofi_genzyme.jpg"},
    {"name": "SAP", "src": "sap.jpg"},
    {"name": "Saphirus", "src": "saphirus.jpg"},
    {"name": "Sas Automotriz Argentina", "src": "sas_automotriz.png"},
    {"name": "Schenker Argentina", "src": "schenker_argentina.png"},
    {"name": "Schott", "src": "schott.jpg"},
    {"name": "Sheraton", "src": "sheraton.jpg"},
    {"name": "Silica Networks", "src": "silica_networks.jpg"},
    {"name": "Sinea Plasticos", "src": "sinea_plasticos.png"},
    {"name": "Sinteplast", "src": "sinteplast.jpg"},
    {"name": "Smurfit Kappa", "src": "smurfit_kappa.jpg"},
    {"name": "Socmer", "src": "socmer.jpg"},
    {"name": "Sonda", "src": "sonda.jpg"},
    {"name": "Symbar", "src": "symbar.jpg"},
    {"name": "Technology Bureau", "src": "technology_bureau.png"},
    {"name": "Telcosur", "src": "telcosur.jpg"},
    {"name": "Tgs", "src": "tgs.jpg"},
    {"name": "Thermomix", "src": "thermomix.png"},
    {"name": "Tiba", "src": "tiba.jpg"},
    {"name": "Ticketek Argentina", "src": "ticketek_argentina.png"},
    {"name": "Toyota", "src": "toyota.png"},
    {"name": "Toyota Tsusho", "src": "toyota_tsusho.png"},
    {"name": "Transener", "src": "transener.jpg"},
    {"name": "Tubhier", "src": "tubhier.jpg"},
    {"name": "Tubos Argentinos", "src": "tubos_argentinos.png"},
    {"name": "Universidad de Morón", "src": "universidad_de_moron.png"},
    {"name": "Unisys", "src": "unisys.png"},
    {"name": "Universal Assistance", "src": "universal_assistance.png"},
    {"name": "UTN", "src": "utn.png"},
    {"name": "Village Cinemas", "src": "village_cinemas.jpg"},
    {"name": "Vital", "src": "vital.jpg"},
    {"name": "Wella Professionals", "src": "wella_professionals.jpg"},
    {"name": "Western Union", "src": "western_union.jpg"},
    {"name": "Whirlpool", "src": "whirlpool.jpg"},
    {"name": "Yacimiento entre lomas", "src": "yacimiento_entre_lomas.jpg"},
    {"name": "Yell Arg SA", "src": "yell_arg.png"},
    {"name": "Yersiplast", "src": "yersiplast.jpg"},
    {"name": "Zurich Santander Seguros", "src": "zurich_santander_seguros.jpg"}
]